ezlogger_xzf/__init__.py
ezlogger_xzf/example.py
ezlogger_xzf-0.0.1.dist-info/METADATA
ezlogger_xzf-0.0.1.dist-info/WHEEL
ezlogger_xzf-0.0.1.dist-info/licenses/LICENSE
ezlogger_xzf-0.0.1.dist-info/RECORD
